chatstream/__init__.py
chatstream/chat_core.py
chatstream/chat_process.py
chatstream/chat_process_mock.py
chatstream/chat_prompt.py
chatstream/chat_stream.py
chatstream/chat_stream_api_appender.py
chatstream/chat_stream_middleware_appender.py
chatstream/default_api_names.py
chatstream/default_api_names_to_path.py
chatstream/default_finish_token.py
chatstream/easy_locale.py
chatstream/merge_dic.py
chatstream/mock_response_example_text.py
chatstream/resource_usage.py
chatstream/util_create_streaming_response.py
chatstream/util_ensure_torch_device.py
chatstream/util_request_id.py
chatstream/util_resource_file_response.py
chatstream/access_control/__init__.py
chatstream/access_control/client_role_authorizer_for_agent.py
chatstream/access_control/client_role_authorizer_for_browser.py
chatstream/access_control/client_role_finalizer.py
chatstream/access_control/client_role_verifier.py
chatstream/access_control/client_role_wrapper.py
chatstream/access_control/default_client_role_grant_middleware.py
chatstream/access_control/role_def_to_client_role.py
chatstream/chat_prompt_presets/__init__.py
chatstream/chat_prompt_presets/chat_prompt_cyberagent_opencalm.py
chatstream/chat_prompt_presets/chat_prompt_databricks_dolly.py
chatstream/chat_prompt_presets/chat_prompt_linecorp_gpt_neox.py
chatstream/chat_prompt_presets/chat_prompt_matsuolab_gpt_neox.py
chatstream/chat_prompt_presets/chat_prompt_metallama_llama2.py
chatstream/chat_prompt_presets/chat_prompt_mosaicml_mpt_chat.py
chatstream/chat_prompt_presets/chat_prompt_openlmresearch_open_llama.py
chatstream/chat_prompt_presets/chat_prompt_rinna_gpt_neox.py
chatstream/chat_prompt_presets/chat_prompt_stabilityai_gpt_neox.py
chatstream/chat_prompt_presets/chat_prompt_stockmark_gpt_neox.py
chatstream/chat_prompt_presets/chat_prompt_togethercomputer_redpajama_incite.py
chatstream/data/__init__.py
chatstream/mock/__init__.py
chatstream/mock/chat_core_probe.py
chatstream/mock/mock_def.py
chatstream/mock/mock_model.py
chatstream-0.3.0.dist-info/LICENSE.md
chatstream-0.3.0.dist-info/METADATA
chatstream-0.3.0.dist-info/WHEEL
chatstream-0.3.0.dist-info/top_level.txt
chatstream-0.3.0.dist-info/RECORD
