Metadata-Version: 2.1
Name: chatstream
Version: 0.3.0
Summary: A streaming chat toolkit for pre-trained large language models(LLM)
Home-page: https://github.com/qualiteg/ChatStream
Author: Qualiteg
Author-email: qualiteger@qualiteg.com
Classifier: Development Status :: 4 - Beta
Classifier: Intended Audience :: Developers
Classifier: License :: OSI Approved :: GNU Affero General Public License v3
Classifier: License :: Other/Proprietary License
Classifier: Programming Language :: Python :: 3.8
Classifier: Programming Language :: Python :: 3.9
Classifier: Programming Language :: Python :: 3.10
Requires-Python: >=3.8
License-File: LICENSE.md
Requires-Dist: transformers
Requires-Dist: torch
Requires-Dist: fastapi
Requires-Dist: fastsession
Requires-Dist: tokflow
Requires-Dist: loadtime >=1.0.6
